pystringtoolkit/__init__.py
pystringtoolkit/case_conversion.py
pystringtoolkit/cases.py
pystringtoolkit/cleaners.py
pystringtoolkit/counting.py
pystringtoolkit/generators.py
pystringtoolkit/validators.py
pystringtoolkit-0.1.4.dist-info/licenses/LICENSE
tests/__init__.py
tests/test_case_conversion.py
tests/test_cases.py
tests/test_cleaners.py
tests/test_counting.py
tests/test_generators.py
tests/test_validators.py
pystringtoolkit-0.1.4.dist-info/METADATA
pystringtoolkit-0.1.4.dist-info/WHEEL
pystringtoolkit-0.1.4.dist-info/top_level.txt
pystringtoolkit-0.1.4.dist-info/RECORD
