Metadata-Version: 2.4
Name: pystringtoolkit
Version: 0.1.4
Summary: Handy string utilities for Python
Home-page: https://github.com/RaeesFatima/pystringtoolkit
Author: Raees Fatima
Project-URL: Source, https://github.com/RaeesFatima/pystringtoolkit
Project-URL: Bug Tracker, https://github.com/RaeesFatima/pystringtoolkit/issues
Classifier: Programming Language :: Python :: 3
Classifier: License :: OSI Approved :: MIT License
Requires-Python: >=3.7
License-File: LICENSE
Dynamic: author
Dynamic: classifier
Dynamic: description
Dynamic: description-content-type
Dynamic: home-page
Dynamic: license-file
Dynamic: project-url
Dynamic: requires-python
Dynamic: summary
